Workbook
Name \\\: #REF!
Name \\\: #REF!
Name \A: #REF!
Name \A: #REF!
Name \B: #REF!
Name \B: #REF!
Name \C: #REF!
Name \C: #REF!
Name \D: #REF!
Name \D: #REF!
Name \E: #REF!
Name \E: #REF!
Name \F: #REF!
Name \F: #REF!
Name \g: #N/A
Name \H: #REF!
Name \H: #REF!
Name \I: #REF!
Name \I: #REF!
Name \J: #REF!
Name \J: #REF!
Name \K: #REF!
Name \K: #REF!
Name \L: #REF!
Name \L: #REF!
Name \M: #REF!
Name \M: #REF!
Name \N: #REF!
Name \N: #REF!
Name \p: #N/A
Name \Q: #REF!
Name \Q: #REF!
Name \R: #REF!
Name \R: #REF!
Name \s: #N/A
Name \T: #REF!
Name \T: #REF!
Name \V: #REF!
Name \V: #REF!
Name \x: #REF!
Name \x: #REF!
Name \z: #REF!
Name \z: #REF!
Name _???205: #REF!
Name _???205: #REF!
Name _?78: #REF!
Name _?78: #REF!
Name _?88: #REF!
Name _?88: #REF!
Name __???205: #REF!
Name __???205: #REF!
Name __?78: #REF!
Name __?78: #REF!
Name __?88: #REF!
Name __?88: #REF!
Name ___???205: #REF!
Name ___???205: #REF!
Name ___?78: #REF!
Name ___?78: #REF!
Name ___?88: #REF!

Sheet Table of Content
A1: AKH Digital
A2: Financial Model
A4: Tab | B4: Description | C4: Link
A5: 1 | B5: Dashboard | C5: Click Here
A6: =+A5+1 -> 2 | B6: At a Glance | C6: Click Here
A7: =+A6+1 -> 3 | B7: PL | C7: Click Here
A8: =+A7+1 -> 4 | B8: BS | C8: Click Here
A9: =+A8+1 -> 5 | B9: CF | C9: Click Here
A10: =+A9+1 -> 6 | B10: Assumption sheet | C10: Click Here
A11: =+A10+1 -> 7 | B11: Revenue Inputs | C11: Click Here
A12: =+A11+1 -> 8 | B12: Revenue Summary | C12: Click Here
A13: =+A12+1 -> 9 | B13: Tokeneconomics | C13: Click Here
A14: =+A13+1 -> 10 | B14: CAPEX | C14: Click Here
A15: =+A14+1 -> 11 | B15: COS | C15: Click Here
A16: =+A15+1 -> 12 | B16: OPEX | C16: Click Here
A17: =+A16+1 -> 13 | B17: Hiring Plan | C17: Click Here
... A23: =+A22+1 -> 19 | B23: LTV CAC | C23: Click Here

Sheet At a Glance
A1: =+'Assumption Sheet'!A1:C1 -> Projected Financials - AKH Digital
B4: Profit and Loss at a Glance | N4: Key Ratios | U4: Return Analysis
C6: 46221 | E6: 46568 | G6: 46934 | I6: 47299 | K6: 47664 | O6: 46203 | P6: 46568 | Q6: 46934 | R6: 46934 | S6: 46934 | X6: Year-0 | Y6: Year-1 | Z6: Year-2 | AA6: Year-3 | AB6: Year-4 | AC6: Year-5 | AD6: IRR
B7: Revenue | C7: =PL!D11 -> 9045749 | D7: =C7/C7 -> 1 | E7: =PL!E11 -> 50952485 | F7: =E7/E7 -> 1 | G7: =PL!F11 -> 1.1170608e+08 | H7: =G7/G7 -> 1 | I7: =PL!G11 -> 1.3593942e+08 | J7: =I7/I7 -> 1 | K7: =PL!H11 -> 1.6227339e+08 | L7: =K7/K7 -> 1 | N7: Sales Growth | O7: N/A | P7: =(E7-C7)/C7 -> 4.6327547 | Q7: =(G7-E7)/E7 -> 1.1923579 | R7: =(I7-G7)/G7 -> 0.21693841 | S7: =(K7-I7)/I7 -> 0.19371839
B8: Cost of Goods Sold | C8: =PL!D16 -> 1716100.4 | D8: =C8/C7 -> 0.18971347 | E8: =PL!E16 -> 17982329 | F8: =E8/E7 -> 0.35292349 | G8: =PL!F16 -> 43894463 | H8: =G8/G7 -> 0.39294604 | I8: =PL!G16 -> 53641221 | J8: =I8/I7 -> 0.39459651 | K8: =PL!H16 -> 64407672 | L8: =K8/K7 -> 0.3969084 | N8: Gross Profit Margin | O8: ='At a Glance'!C9/'At a Glance'!C7 -> 0.81028653 | P8: ='At a Glance'!E9/'At a Glance'!E7 -> 0.64707651 | Q8: ='At a Glance'!G9/'At a Glance'!G7 -> 0.60705396 | R8: =(I8-G8)/G8 -> 0.22204983 | S8: =(K8-I8)/I8 -> 0.20071225 | U8: Exit Multiple @ | V8: 2
B9: Gross Profit | C9: =C7-C8 -> 7329648.6 | D9: =C9/C7 -> 0.81028653 | E9: =E7-E8 -> 32970156 | F9: =E9/E7 -> 0.64707651 | G9: =G7-G8 -> 67811619 | H9: =G9/G7 -> 0.60705396 | I9: =I7-I8 -> 82298202 | J9: =I9/I7 -> 0.60540349 | K9: =K7-K8 -> 97865717 | L9: =K9/K7 -> 0.6030916 | N9: Return on Capital | O9: =AE9 -> 0 | P9: =AE10 -> 0 | Q9: =AE11 -> 0 | R9: =AE12 -> 0 | S9: =AE13 -> 0 | V9: Exit in Year-1 | X9: =-K44 -> -1400000 | Y9: =C12*$V$8 -> 5059297.1 | Z9: 0 | AA9: 0 | AD9: =IFERROR(IRR(X9:Y9),"-") -> 2.6137836
B10: Operating Expenses | C10: =PL!D47 -> 4800000 | D10: =C10/C7 -> 0.53063599 | E10: =PL!E47 -> 6396720 | F10: =E10/E7 -> 0.12554285 | G10: =PL!F47 -> 8340772 | H10: =G10/G7 -> 0.074667125 | I10: =PL!G47 -> 12044485 | J10: =I10/I7 -> 0.088601856 | K10: =PL!H47 -> 14714498 | L10: =K10/K7 -> 0.090677208 | N10: Profit Margin | O10: ='At a Glance'!C11/'At a Glance'!C7 -> 0.20649905 | P10: ='At a Glance'!E11/'At a Glance'!E7 -> 0.41586065 | Q10: ='At a Glance'!G11/'At a Glance'!G7 -> 0.42500044 | R10: =(I10-G10)/G10 -> 0.44404921 | S10: =(K10-I10)/I10 -> 0.22167926 | V10: Exit in Year-2 | X10: =+X9 -> -1400000 | Y10: =$Y$7 -> 0 | Z10: =E12*V8 -> 53146872 | AA10: =$AA$7 -> 0 | AD10: =IFERROR(IRR(X10:Z10),"-") -> 5.1613352
B11: Net Income | C11: =PL!D57 -> 1867938.6 | D11: =C11/C7 -> 0.20649905 | E11: =PL!E57 -> 21189134 | F11: =E11/E7 -> 0.41586065 | G11: =PL!F57 -> 47475135 | H11: =G11/G7 -> 0.42500044 | I11: =PL!G57 -> 56090338 | J11: =I11/I7 -> 0.41261274 | K11: =PL!H57 -> 66414921 | L11: =K11/K7 -> 0.40927795 | V11: Exit in Year-3 | X11: =+X10 -> -1400000 | Y11: =$Y$7 -> 0 | Z11: =$Z$7 -> 0 | AA11: =G12*V8 -> 1.1894169e+08 | AD11: =IFERROR(IRR(X11:AA11),"-") -> 3.3961115
B12: EBITDA | C12: =PL!D48 -> 2529648.6 | D12: =C12/C7 -> 0.27965054 | E12: =PL!E48 -> 26573436 | F12: =E12/E7 -> 0.52153366 | G12: =PL!F48 -> 59470847 | H12: =G12/G7 -> 0.53238683 | I12: =PL!G48 -> 70253716 | J12: =I12/I7 -> 0.51680164 | K12: =PL!H48 -> 83151220 | L12: =K12/K7 -> 0.51241439 | N12: Burn Rate | V12: Exit in Year-4 | X12: =+X11 -> -1400000 | Y12: =$Y$7 -> 0 | Z12: =$Z$7 -> 0 | AA12: =$AA$7 -> 0 | AB12: =I12*V8 -> 1.4050743e+08 | AD12: =IFERROR(IRR(X12:AB12),"-") -> 2.1651392
B13: EBITDA is earnings before interest, tax, depreciation, and amortization. | V13: Exit in Year-5 | X13: =+X12 -> -1400000 | Y13: =$Y$7 -> 0 | Z13: =$Z$7 -> 0 | AA13: =$AA$7 -> 0 | AC13: =K12*V8 -> 1.6630244e+08 | AD13: =IFERROR(IRR(X13:AC13),"-") -> 2.3013582 | AO13: =210/42 -> 5
C14: 1 | E14: 2 | G14: 3 | I14: 4 | K14: 5 | O14: =O6 -> 46203 | P14: =P6 -> 46568 | Q14: =Q6 -> 46934 | R14: =R6 -> 46934 | S14: =S6 -> 46934
C15: 12 | E15: 24 | G15: 36 | I15: 48 | K15: 60 | N15: Total Operating Expenses | O15: =OPEX!D32 -> 1908000 | P15: =OPEX!E32 -> 2098800 | Q15: =OPEX!F32 -> 2308680 | R15: =OPEX!G32 -> 2539548 | S15: =OPEX!H32 -> 2793502.8
B16: CAC
C18: =+C6 -> 46221 | E18: =+E6 -> 46568 | G18: =+G6 -> 46934 | I18: =+I6 -> 47299 | K18: =+K6 -> 47664 | N18: Annually Gross Burn | O18: =O15 -> 1908000 | P18: =P15 -> 2098800 | Q18: =Q15 -> 2308680 | R18: =R15 -> 2539548 | S18: =S15 -> 2793502.8
B19: Marketing & Sales Expense
N20: Net Cash Flow | O20: =CF!D27 -> 2537475.6 | P20: =CF!E27 -> 19684611 | Q20: =CF!F27 -> 46786013 | R20: =CF!G27 -> 55842429 | S20: =CF!H27 -> 66078150
B21: Sales and Marketing | C21: =+OPEX!D7 -> 300000 | E21: =OPEX!E7 -> 330000 | G21: =OPEX!F7 -> 363000 | I21: =OPEX!G7 -> 399300 | K21: =OPEX!G7 -> 399300
B22: Sales and Marketing Salaries | C22: =+'Hiring Plan'!I17+'Hiring Plan'!I18 -> 0 | E22: =+'Hiring Plan'!J17+'Hiring Plan'!J18 -> 0 | G22: =+'Hiring Plan'!K17+'Hiring Plan'!K18 -> 0 | I22: =+'Hiring Plan'!L17+'Hiring Plan'!L18 -> 0 | K22: =+'Hiring Plan'!M17+'Hiring Plan'!M18 -> 0 | N22: Runway | O22: =O20/O18 -> 1.3299138 | P22: =P20/P18 -> 9.3789838 | Q22: =Q20/Q18 -> 20.265265 | R22: =R20/R18 -> 21.989121 | S22: =S20/S18 -> 23.654227
B23: =Total Sales Expense | C23: =+SUM(C21:C22) -> 300000 | E23: =+SUM(E21:E22) -> 330000 | G23: =+SUM(G21:G22) -> 363000 | I23: =+SUM(I21:I22) -> 399300 | K23: =+SUM(K21:K22) -> 399300
B25: New Business Sales Expense | C25: =$C$27*C23 -> 300000 | E25: =$C$27*E23 -> 330000 | G25: =$C$27*G23 -> 363000 | I25: =$C$27*I23 -> 399300 | K25: =$C$27*K23 -> 399300
B27: % Dedicated to New Business | C27: 1
B29: Total New Customer Acquisition Expense | C29: =+C25 -> 300000 | E29: =+E25 -> 330000 | G29: =+G25 -> 363000 | I29: =+I25 -> 399300 | K29: =+K25 -> 399300
B31: No. of Unit | C31: =+'LTV CAC'!E14 -> 100 | E31: =+'LTV CAC'!F14 -> 300 | G31: ='LTV CAC'!G14 -> 500 | I31: ='LTV CAC'!H14 -> 700 | K31: ='LTV CAC'!I14 -> 900
B33: CAC | C33: =C29/C31 -> 3000 | E33: =E29/E31 -> 1100 | G33: =G29/G31 -> 726 | I33: =I29/I31 -> 570.42857 | K33: =K29/K31 -> 443.66667
B34: CAC per Customer | C34: =C33/C31 -> 30 | E34: =E33/E31 -> 3.6666667 | G34: =G33/G31 -> 1.452 | I34: =I33/I31 -> 0.81489796 | K34: =K33/K31 -> 0.49296296
I44: Total Funds Raised: | K44: ='Transaction Capital'!C10 -> 1400000
I45: Months Covered: | K45: 12
I47: Use of Initial Funds:
I48: =+UoF!B6 -> Core Protocol & Smart Contract Engineering | K48: =+UoF!D6 -> 196000
I49: =+UoF!B7 -> Exchange Platform Development | K49: =+UoF!D7 -> 270000
I50: =+UoF!B8 -> Custody Infrastructure & Security Systems | K50: =+UoF!D8 -> 125000
I51: =+UoF!B9 -> Front-End / UX / App | K51: =+UoF!D9 -> 134000
I52: =+UoF!B10 -> Regulatory & Compliance | K52: =+UoF!D10 -> 125000
I53: =+UoF!B11 -> Data / Analytics / Backend | K53: =+UoF!D11 -> 84000
I55: Total | K55: =K48+K50+K51+K52+K49+K53 -> 934000
B76: Need Additional Graphs or Ratios?
B77: We can help!
B78: Click here to contact us or email us at
C88: =C34 -> 30 | D88: =E34 -> 3.6666667 | E88: =G34 -> 1.452 | F88: =I34 -> 0.81489796 | G88: =K34 -> 0.49296296
B121: Month | C121: 0 | D121: 1 | E121: 2 | F121: 3 | G121: 4 | H121: 5 | I121: 6 | J121: 7 | K121: 8 | L121: 9 | M121: 10 | N121: 11 | O121: 12 | P121: 13 | Q121: 14 | R121: 15 | S121: 16 | T121: 17 | U121: 18 | V121: 19 | W121: 20 | X121: 21 | Y121: 22 | Z121: 23 | AA121: 24 | AB121: 25 | AC121: 26 | AD121: 27 | AE121: 28 | AF121: 29 | AG121: 30 | AH121: 31 | AI121: 32 | AJ121: 33 | AK121: 34 | AL121: 35 | AM121: 36 | AN121: 37 | AO121: 38 | AP121: 39 | AQ121: 40 | AR121: 41 | AS121: 42 | AT121: 43 | AU121: 44 | AV121: 45 | AW121: 46 | AX121: 47 | AY121: 48 | AZ121: 49 | BA121: 50 | BB121: 51 | BC121: 52 | BD121: 53 | BE121: 54 | BF121: 55 | BG121: 56 | BH121: 57 | BI121: 58 | BJ121: 59 | BK121: 60
B122: Debt | C122: {=TRANSPOSE('Loan Amortization'!D13:D72)} -> 0 | D122: 0 | E122: 0 | F122: 0 | G122: 0 | H122: 0 | I122: 0 | J122: 0 | K122: 0 | L122: 0 | M122: 0 | N122: 0 | O122: 0 | P122: 0 | Q122: 0 | R122: 0 | S122: 0 | T122: 0 | U122: 0 | V122: 0 | W122: 0 | X122: 0 | Y122: 0 | Z122: 0 | AA122: 0 | AB122: 0 | AC122: 0 | AD122: 0 | AE122: 0 | AF122: 0 | AG122: 0 | AH122: 0 | AI122: 0 | AJ122: 0 | AK122: 0 | AL122: 0 | AM122: 0 | AN122: 0 | AO122: 0 | AP122: 0 | AQ122: 0 | AR122: 0 | AS122: 0 | AT122: 0 | AU122: 0 | AV122: 0 | AW122: 0 | AX122: 0 | AY122: 0 | AZ122: 0 | BA122: 0 | BB122: 0 | BC122: 0 | BD122: 0 | BE122: 0 | BF122: 0 | BG122: 0 | BH122: 0 | BI122: 0 | BJ122: 0 | BK122: #N/A
B123: Paid in Capital | C123: =CF!D48 -> 1400000 | D123: =CF!E48 -> 0 | E123: =CF!F48 -> 0 | F123: =CF!G48 -> 0 | G123: =CF!H48 -> 0 | H123: =CF!I48 -> 0 | I123: =CF!J48 -> 0 | J123: =CF!K48 -> 0 | ... BK123: =CF!BL48 -> 0
B124: Cumulative Cash From Operations | C124: =CF!D42 -> -282698.63 | D124: =CF!E42 -> -227153.15 | E124: =CF!F42 -> -223559.73 | F124: =CF!G42 -> 122107.44 | G124: =CF!H42 -> 208957.61 | H124: =CF!I42 -> 216519.96 | I124: =CF!J42 -> 225360.12 | J124: =CF!K42 -> 236863.88 | ... BK124: =CF!BL42 -> 0

Sheet Dashboard
X6: =AVERAGE('LTV CAC'!E17:I17) -> 586089.6
X7: =AVERAGE(PL!D49:H49) -> 0.47255741
C8: QUICK LINKS | M8: UNIT ECONOMICS
AB11: Months With Net Loss
AB14: =MATCH(0,PL!D114:BK114,1) -> 3
G21: KEY METRICS
F36: FINANCIAL STATEMENTS

Sheet Tokeneconomics Structure
B2: Summary
B3: Company | C3: AKH Digital | E3: Total Token Allocations
B4: Token | C4: FVC | E4: Token Allocation | G4: Total Tokens (%) | H4: Token Amount
B5: Soft Cap | C5: =+BK28 -> 400000000 | E5: =+B34 -> Founders, Team & Partners | G5: =C34/$C$41 -> 0.25 | H5: =C34 -> 250000000 | J5: =+E5 -> Founders, Team & Partners | K5: =+G5 -> 0.25
B6: Total Token Supply | C6: 1000000000 | E6: =+B35 -> Key Partnerships & Projects | G6: =C35/$C$41 -> 0.2 | H6: =C35 -> 200000000 | J6: =+E6 -> Key Partnerships & Projects | K6: =+G6 -> 0.2
B7: Initial Circulating Supply | C7: =+D25 -> 200000000 | E7: =+B36 -> Ecosystem & Web3 Platform | G7: =C36/$C$41 -> 0.2 | H7: =C36 -> 200000000 | J7: =+E7 -> Ecosystem & Web3 Platform | K7: =+G7 -> 0.2
B8: Initial Circulating Supply % | C8: =+D25/C41 -> 0.2 | D8: 1 | E8: =+B37 -> Marketing & Community Growth | G8: =C37/$C$41 -> 0.15 | H8: =C37 -> 150000000 | I8: =+#REF!+1 -> #REF! | J8: =+E8 -> Marketing & Community Growth | K8: =+G8 -> 0.15 | L8: =+K8+1 -> 1.15 | M8: =+L8+1 -> 2.15 | N8: =+M8+1 -> 3.15 | O8: =+N8+1 -> 4.15 | P8: =+O8+1 -> 5.15 | Q8: =+P8+1 -> 6.15 | R8: =+Q8+1 -> 7.15 | S8: =+R8+1 -> 8.15 | ... BK8: =+BJ8+1 -> 52.15
B9: Public Sale Token Price | C9: =+AVERAGE(D27:BK27) -> 0.275 | E9: =+B38 -> Treasury & Reserve | G9: =C38/$C$41 -> 0.14 | H9: =C38 -> 140000000 | J9: =+E9 -> Treasury & Reserve | K9: =+G9 -> 0.14
B10: Initial Market Cap | C10: =+C16 -> 10000000 | E10: =+B39 -> Staking Rewards | G10: =C39/$C$41 -> 0.05 | H10: =C39 -> 50000000 | J10: =+E10 -> Staking Rewards | K10: =+G10 -> 0.05
E11: =+B40 -> Charitable Initiatives | G11: =C40/$C$41 -> 0.01 | H11: =C40 -> 10000000 | J11: =+E11 -> Charitable Initiatives | K11: =+G11 -> 0.01
B12: Sale Summary
B13: Amount to be Raised | C13: =(350+450+600)*1000 -> 1400000 | E13: All Tokens | G13: =+SUM(G5:G11) -> 1 | H13: =+SUM(H5:H11) -> 1000000000
B14: Tokens to be Sold | C14: =+BK25 -> 800000000
B15: % Supply | C15: =+BK28/C41 -> 0.4
B16: Initial Market Cap | C16: =+D28 -> 10000000
B17: Fully Diluted Market Cap | C17: =+BK29 -> 500000000
B22: Tokenomics
B24: Metric | D24: Month 1 | E24: Month 2 | F24: Month 3 | G24: Month 4 | H24: Month 5 | I24: Month 6 | J24: Month 7 | K24: Month 8 | L24: Month 9 | M24: Month 10 | N24: Month 11 | O24: Month 12 | P24: Month 13 | Q24: Month 14 | R24: Month 15 | S24: Month 16 | T24: Month 17 | U24: Month 18 | V24: Month 19 | W24: Month 20 | X24: Month 21 | Y24: Month 22 | Z24: Month 23 | AA24: Month 24 | AB24: Month 25 | AC24: Month 26 | AD24: Month 27 | AE24: Month 28 | AF24: Month 29 | AG24: Month 30 | AH24: Month 31 | AI24: Month 32 | AJ24: Month 33 | AK24: Month 34 | AL24: Month 35 | AM24: Month 36 | AN24: Month 37 | AO24: Month 38 | AP24: Month 39 | AQ24: Month 40 | AR24: Month 41 | AS24: Month 42 | AT24: Month 43 | AU24: Month 44 | AV24: Month 45 | AW24: Month 46 | AX24: Month 47 | AY24: Month 48 | AZ24: Month 49 | BA24: Month 50 | BB24: Month 51 | BC24: Month 52 | BD24: Month 53 | BE24: Month 54 | BF24: Month 55 | BG24: Month 56 | BH24: Month 57 | BI24: Month 58 | BJ24: Month 59 | BK24: Month 60
B25: Circulating Supply (Tokens) | D25: 200000000 | E25: 210169492 | F25: 220338983 | G25: 230508475 | H25: 240677966 | I25: 250847458 | J25: 261016949 | K25: 271186441 | L25: 281355932 | M25: 291525424 | N25: 301694915 | O25: 311864407 | P25: 322033898 | Q25: 332203390 | R25: 342372881 | S25: 352542373 | T25: 362711864 | U25: 372881356 | V25: 383050847 | W25: 393220339 | X25: 403389831 | Y25: 413559322 | Z25: 423728814 | AA25: 433898305 | AB25: 444067797 | AC25: 454237288 | AD25: 464406780 | AE25: 474576271 | AF25: 484745763 | AG25: 494915254 | AH25: 505084746 | AI25: 515254237 | AJ25: 525423729 | AK25: 535593220 | AL25: 545762712 | AM25: 555932203 | AN25: 566101695 | AO25: 576271186 | AP25: 586440678 | AQ25: 596610169 | AR25: 606779661 | AS25: 616949153 | AT25: 627118644 | AU25: 637288136 | AV25: 647457627 | AW25: 657627119 | AX25: 667796610 | AY25: 677966102 | AZ25: 688135593 | BA25: 698305085 | BB25: 708474576 | BC25: 718644068 | BD25: 728813559 | BE25: 738983051 | BF25: 749152542 | BG25: 759322034 | BH25: 769491525 | BI25: 779661017 | BJ25: 789830508 | BK25: 800000000
B26: Circulating % of Total | D26: 20 | E26: 21.0169 | F26: 22.0339 | G26: 23.0508 | H26: 24.0678 | I26: 25.0847 | J26: 26.1017 | K26: 27.1186 | L26: 28.1356 | M26: 29.1525 | N26: 30.1695 | O26: 31.1864 | P26: 32.2034 | Q26: 33.2203 | R26: 34.2373 | S26: 35.2542 | T26: 36.2712 | U26: 37.2881 | V26: 38.3051 | W26: 39.322 | X26: 40.339 | Y26: 41.3559 | Z26: 42.3729 | AA26: 43.3898 | AB26: 44.4068 | AC26: 45.4237 | AD26: 46.4407 | AE26: 47.4576 | AF26: 48.4746 | AG26: 49.4915 | AH26: 50.5085 | AI26: 51.5254 | AJ26: 52.5424 | AK26: 53.5593 | AL26: 54.5763 | AM26: 55.5932 | AN26: 56.6102 | AO26: 57.6271 | AP26: 58.6441 | AQ26: 59.661 | AR26: 60.678 | AS26: 61.6949 | AT26: 62.7119 | AU26: 63.7288 | AV26: 64.7458 | AW26: 65.7627 | AX26: 66.7797 | AY26: 67.7966 | AZ26: 68.8136 | BA26: 69.8305 | BB26: 70.8475 | BC26: 71.8644 | BD26: 72.8814 | BE26: 73.8983 | BF26: 74.9153 | BG26: 75.9322 | BH26: 76.9492 | BI26: 77.9661 | BJ26: 78.9831 | BK26: 80
B27: Estimated Token Price (GBP) | D27: 0.05 | E27: 0.057627 | F27: 0.065254 | G27: 0.072881 | H27: 0.080508 | I27: 0.088136 | J27: 0.095763 | K27: 0.10339 | L27: 0.111017 | M27: 0.118644 | N27: 0.126271 | O27: 0.133898 | P27: 0.141525 | Q27: 0.149153 | R27: 0.15678 | S27: 0.164407 | T27: 0.172034 | U27: 0.179661 | V27: 0.187288 | W27: 0.194915 | X27: 0.202542 | Y27: 0.210169 | Z27: 0.217797 | AA27: 0.225424 | AB27: 0.233051 | AC27: 0.240678 | AD27: 0.248305 | AE27: 0.255932 | AF27: 0.263559 | AG27: 0.271186 | AH27: 0.278814 | AI27: 0.286441 | AJ27: 0.294068 | AK27: 0.301695 | AL27: 0.309322 | AM27: 0.316949 | AN27: 0.324576 | AO27: 0.332203 | AP27: 0.339831 | AQ27: 0.347458 | AR27: 0.355085 | AS27: 0.362712 | AT27: 0.370339 | AU27: 0.377966 | AV27: 0.385593 | AW27: 0.39322 | AX27: 0.400847 | AY27: 0.408475 | AZ27: 0.416102 | BA27: 0.423729 | BB27: 0.431356 | BC27: 0.438983 | BD27: 0.44661 | BE27: 0.454237 | BF27: 0.461864 | BG27: 0.469492 | BH27: 0.477119 | BI27: 0.484746 | BJ27: 0.492373 | BK27: 0.5
B28: Market Cap (Circulating GBP) | D28: 10000000 | E28: 12111462 | F28: 14378052 | G28: 16799770 | H28: 19376616 | I28: 22108589 | J28: 24995691 | K28: 28037920 | L28: 31235277 | M28: 34587762 | N28: 38095375 | O28: 41758115 | P28: 45575984 | Q28: 49548980 | R28: 53677104 | S28: 57960356 | T28: 62398736 | U28: 66992244 | V28: 71740879 | W28: 76644642 | X28: 81703533 | Y28: 86917552 | Z28: 92286699 | AA28: 97810974 | AB28: 1.0349038e+08 | AC28: 1.0932491e+08 | AD28: 1.1531456e+08 | AE28: 1.2145935e+08 | AF28: 1.2775926e+08 | AG28: 1.3421431e+08 | AH28: 1.4082448e+08 | AI28: 1.4758977e+08 | AJ28: 1.545102e+08 | AK28: 1.6158575e+08 | AL28: 1.6881643e+08 | AM28: 1.7620224e+08 | AN28: 1.8374318e+08 | AO28: 1.9143924e+08 | AP28: 1.9929043e+08 | AQ28: 2.0729675e+08 | AR28: 2.154582e+08 | AS28: 2.2377478e+08 | AT28: 2.3224648e+08 | AU28: 2.4087331e+08 | AV28: 2.4965527e+08 | AW28: 2.5859236e+08 | AX28: 2.6768457e+08 | AY28: 2.7693192e+08 | AZ28: 2.8633439e+08 | BA28: 2.9589199e+08 | BB28: 3.0560471e+08 | BC28: 3.1547257e+08 | BD28: 3.2549555e+08 | BE28: 335673657 | BF28: 3.4600689e+08 | BG28: 3.5649526e+08 | BH28: 3.6713875e+08 | BI28: 3.7793737e+08 | BJ28: 3.8889112e+08 | BK28: 400000000
B29: Fully Diluted Valuation (FDV GBP) | D29: 50000000 | E29: 57627119 | F29: 65254237 | G29: 72881356 | H29: 80508475 | I29: 88135593 | J29: 95762712 | K29: 1.0338983e+08 | L29: 1.1101695e+08 | M29: 1.1864407e+08 | N29: 1.2627119e+08 | O29: 1.3389831e+08 | P29: 1.4152542e+08 | Q29: 1.4915254e+08 | R29: 1.5677966e+08 | S29: 1.6440678e+08 | T29: 1.720339e+08 | U29: 1.7966102e+08 | V29: 1.8728814e+08 | W29: 1.9491525e+08 | X29: 2.0254237e+08 | Y29: 2.1016949e+08 | Z29: 2.1779661e+08 | AA29: 2.2542373e+08 | AB29: 2.3305085e+08 | AC29: 2.4067797e+08 | AD29: 2.4830508e+08 | AE29: 2.559322e+08 | AF29: 2.6355932e+08 | AG29: 2.7118644e+08 | AH29: 2.7881356e+08 | AI29: 2.8644068e+08 | AJ29: 2.940678e+08 | AK29: 3.0169492e+08 | AL29: 3.0932203e+08 | AM29: 3.1694915e+08 | AN29: 3.2457627e+08 | AO29: 3.3220339e+08 | AP29: 3.3983051e+08 | AQ29: 3.4745763e+08 | AR29: 3.5508475e+08 | AS29: 3.6271186e+08 | AT29: 3.7033898e+08 | AU29: 3.779661e+08 | AV29: 3.8559322e+08 | AW29: 3.9322034e+08 | AX29: 4.0084746e+08 | AY29: 4.0847458e+08 | AZ29: 4.1610169e+08 | BA29: 4.2372881e+08 | BB29: 4.3135593e+08 | BC29: 4.3898305e+08 | BD29: 4.4661017e+08 | BE29: 4.5423729e+08 | BF29: 4.6186441e+08 | BG29: 4.6949153e+08 | BH29: 4.7711864e+08 | BI29: 4.8474576e+08 | BJ29: 4.9237288e+08 | BK29: 500000000
B31: Cumulative Token Sale Schedule
B33: Category | C33: Total Allocation (Tokens) | D33: Month 1 | E33: Month 2 | F33: Month 3 | G33: Month 4 | H33: Month 5 | I33: Month 6 | J33: Month 7 | K33: Month 8 | L33: Month 9 | M33: Month 10 | N33: Month 11 | O33: Month 12 | P33: Month 13 | Q33: Month 14 | R33: Month 15 | S33: Month 16 | T33: Month 17 | U33: Month 18 | V33: Month 19 | W33: Month 20 | X33: Month 21 | Y33: Month 22 | Z33: Month 23 | AA33: Month 24 | AB33: Month 25 | AC33: Month 26 | AD33: Month 27 | AE33: Month 28 | AF33: Month 29 | AG33: Month 30 | AH33: Month 31 | AI33: Month 32 | AJ33: Month 33 | AK33: Month 34 | AL33: Month 35 | AM33: Month 36 | AN33: Month 37 | AO33: Month 38 | AP33: Month 39 | AQ33: Month 40 | AR33: Month 41 | AS33: Month 42 | AT33: Month 43 | AU33: Month 44 | AV33: Month 45 | AW33: Month 46 | AX33: Month 47 | AY33: Month 48 | AZ33: Month 49 | BA33: Month 50 | BB33: Month 51 | BC33: Month 52 | BD33: Month 53 | BE33: Month 54 | BF33: Month 55 | BG33: Month 56 | BH33: Month 57 | BI33: Month 58 | BJ33: Month 59 | BK33: Month 60
B34: Founders, Team & Partners | C34: 250000000 | D34: 0 | E34: 0 | F34: 0 | G34: 0 | H34: 0 | I34: 0 | J34: 0 | K34: 0 | L34: 0 | M34: 0 | N34: 0 | O34: 0 | P34: 5208333 | Q34: 10416667 | R34: 15625000 | S34: 20833333 | T34: 26041667 | U34: 31250000 | V34: 36458333 | W34: 41666667 | X34: 46875000 | Y34: 52083333 | Z34: 57291667 | AA34: 62500000 | AB34: 67708333 | AC34: 72916667 | AD34: 78125000 | AE34: 83333333 | AF34: 88541667 | AG34: 93750000 | AH34: 98958333 | AI34: 104166667 | AJ34: 109375000 | AK34: 114583333 | AL34: 119791667 | AM34: 125000000 | AN34: 130208333 | AO34: 135416667 | AP34: 140625000 | AQ34: 145833333 | AR34: 151041667 | AS34: 156250000 | AT34: 161458333 | AU34: 166666667 | AV34: 171875000 | AW34: 177083333 | AX34: 182291667 | AY34: 187500000 | AZ34: 192708333 | BA34: 197916667 | BB34: 203125000 | BC34: 208333333 | BD34: 213541667 | BE34: 218750000 | BF34: 223958333 | BG34: 229166667 | BH34: 234375000 | BI34: 239583333 | BJ34: 244791667 | BK34: 250000000
B35: Key Partnerships & Projects | C35: 200000000 | D35: 4166667 | E35: 8333333 | F35: 12500000 | G35: 16666667 | H35: 20833333 | I35: 25000000 | J35: 29166667 | K35: 33333333 | L35: 37500000 | M35: 41666667 | N35: 45833333 | O35: 50000000 | P35: 54166667 | Q35: 58333333 | R35: 62500000 | S35: 66666667 | T35: 70833333 | U35: 75000000 | V35: 79166667 | W35: 83333333 | X35: 87500000 | Y35: 91666667 | Z35: 95833333 | AA35: 100000000 | AB35: 104166667 | AC35: 108333333 | AD35: 112500000 | AE35: 116666667 | AF35: 120833333 | AG35: 125000000 | AH35: 129166667 | AI35: 133333333 | AJ35: 137500000 | AK35: 141666667 | AL35: 145833333 | AM35: 150000000 | AN35: 154166667 | AO35: 158333333 | AP35: 162500000 | AQ35: 166666667 | AR35: 170833333 | AS35: 175000000 | AT35: 179166667 | AU35: 183333333 | AV35: 187500000 | AW35: 191666667 | AX35: 195833333 | AY35: 200000000 | AZ35: 200000000 | BA35: 200000000 | BB35: 200000000 | BC35: 200000000 | BD35: 200000000 | BE35: 200000000 | BF35: 200000000 | BG35: 200000000 | BH35: 200000000 | BI35: 200000000 | BJ35: 200000000 | BK35: 200000000
B36: Ecosystem & Web3 Platform | C36: 200000000 | D36: 5555556 | E36: 11111111 | F36: 16666667 | G36: 22222222 | H36: 27777778 | I36: 33333333 | J36: 38888889 | K36: 44444444 | L36: 50000000 | M36: 55555556 | N36: 61111111 | O36: 66666667 | P36: 72222222 | Q36: 77777778 | R36: 83333333 | S36: 88888889 | T36: 94444444 | U36: 100000000 | V36: 105555556 | W36: 111111111 | X36: 116666667 | Y36: 122222222 | Z36: 127777778 | AA36: 133333333 | AB36: 138888889 | AC36: 144444444 | AD36: 150000000 | AE36: 155555556 | AF36: 161111111 | AG36: 166666667 | AH36: 172222222 | AI36: 177777778 | AJ36: 183333333 | AK36: 188888889 | AL36: 194444444 | AM36: 200000000 | AN36: 200000000 | AO36: 200000000 | AP36: 200000000 | AQ36: 200000000 | AR36: 200000000 | AS36: 200000000 | AT36: 200000000 | AU36: 200000000 | AV36: 200000000 | AW36: 200000000 | AX36: 200000000 | AY36: 200000000 | AZ36: 200000000 | BA36: 200000000 | BB36: 200000000 | BC36: 200000000 | BD36: 200000000 | BE36: 200000000 | BF36: 200000000 | BG36: 200000000 | BH36: 200000000 | BI36: 200000000 | BJ36: 200000000 | BK36: 200000000
B37: Marketing & Community Growth | C37: 150000000 | D37: 4166667 | E37: 8333333 | F37: 12500000 | G37: 16666667 | H37: 20833333 | I37: 25000000 | J37: 29166667 | K37: 33333333 | L37: 37500000 | M37: 41666667 | N37: 45833333 | O37: 50000000 | P37: 54166667 | Q37: 58333333 | R37: 62500000 | S37: 66666667 | T37: 70833333 | U37: 75000000 | V37: 79166667 | W37: 83333333 | X37: 87500000 | Y37: 91666667 | Z37: 95833333 | AA37: 100000000 | AB37: 104166667 | AC37: 108333333 | AD37: 112500000 | AE37: 116666667 | AF37: 120833333 | AG37: 125000000 | AH37: 129166667 | AI37: 133333333 | AJ37: 137500000 | AK37: 141666667 | AL37: 145833333 | AM37: 150000000 | AN37: 150000000 | AO37: 150000000 | AP37: 150000000 | AQ37: 150000000 | AR37: 150000000 | AS37: 150000000 | AT37: 150000000 | AU37: 150000000 | AV37: 150000000 | AW37: 150000000 | AX37: 150000000 | AY37: 150000000 | AZ37: 150000000 | BA37: 150000000 | BB37: 150000000 | BC37: 150000000 | BD37: 150000000 | BE37: 150000000 | BF37: 150000000 | BG37: 150000000 | BH37: 150000000 | BI37: 150000000 | BJ37: 150000000 | BK37: 150000000
B38: Treasury & Reserve | C38: 140000000 | D38: 140000000 | E38: 140000000 | F38: 140000000 | G38: 140000000 | H38: 140000000 | I38: 140000000 | J38: 140000000 | K38: 140000000 | L38: 140000000 | M38: 140000000 | N38: 140000000 | O38: 140000000 | P38: 140000000 | Q38: 140000000 | R38: 140000000 | S38: 140000000 | T38: 140000000 | U38: 140000000 | V38: 140000000 | W38: 140000000 | X38: 140000000 | Y38: 140000000 | Z38: 140000000 | AA38: 140000000 | AB38: 140000000 | AC38: 140000000 | AD38: 140000000 | AE38: 140000000 | AF38: 140000000 | AG38: 140000000 | AH38: 140000000 | AI38: 140000000 | AJ38: 140000000 | AK38: 140000000 | AL38: 140000000 | AM38: 140000000 | AN38: 140000000 | AO38: 140000000 | AP38: 140000000 | AQ38: 140000000 | AR38: 140000000 | AS38: 140000000 | AT38: 140000000 | AU38: 140000000 | AV38: 140000000 | AW38: 140000000 | AX38: 140000000 | AY38: 140000000 | AZ38: 140000000 | BA38: 140000000 | BB38: 140000000 | BC38: 140000000 | BD38: 140000000 | BE38: 140000000 | BF38: 140000000 | BG38: 140000000 | BH38: 140000000 | BI38: 140000000 | BJ38: 140000000 | BK38: 140000000
B39: Staking Rewards | C39: 50000000 | D39: 1041667 | E39: 2083333 | F39: 3125000 | G39: 4166667 | H39: 5208333 | I39: 6250000 | J39: 7291667 | K39: 8333333 | L39: 9375000 | M39: 10416667 | N39: 11458333 | O39: 12500000 | P39: 13541667 | Q39: 14583333 | R39: 15625000 | S39: 16666667 | T39: 17708333 | U39: 18750000 | V39: 19791667 | W39: 20833333 | X39: 21875000 | Y39: 22916667 | Z39: 23958333 | AA39: 25000000 | AB39: 26041667 | AC39: 27083333 | AD39: 28125000 | AE39: 29166667 | AF39: 30208333 | AG39: 31250000 | AH39: 32291667 | AI39: 33333333 | AJ39: 34375000 | AK39: 35416667 | AL39: 36458333 | AM39: 37500000 | AN39: 38541667 | AO39: 39583333 | AP39: 40625000 | AQ39: 41666667 | AR39: 42708333 | AS39: 43750000 | AT39: 44791667 | AU39: 45833333 | AV39: 46875000 | AW39: 47916667 | AX39: 48958333 | AY39: 50000000 | AZ39: 50000000 | BA39: 50000000 | BB39: 50000000 | BC39: 50000000 | BD39: 50000000 | BE39: 50000000 | BF39: 50000000 | BG39: 50000000 | BH39: 50000000 | BI39: 50000000 | BJ39: 50000000 | BK39: 50000000
B40: Charitable Initiatives | C40: 10000000 | D40: 416667 | E40: 833333 | F40: 1250000 | G40: 1666667 | H40: 2083333 | I40: 2500000 | J40: 2916667 | K40: 3333333 | L40: 3750000 | M40: 4166667 | N40: 4583333 | O40: 5000000 | P40: 5416667 | Q40: 5833333 | R40: 6250000 | S40: 6666667 | T40: 7083333 | U40: 7500000 | V40: 7916667 | W40: 8333333 | X40: 8750000 | Y40: 9166667 | Z40: 9583333 | AA40: 10000000 | AB40: 10000000 | AC40: 10000000 | AD40: 10000000 | AE40: 10000000 | AF40: 10000000 | AG40: 10000000 | AH40: 10000000 | AI40: 10000000 | AJ40: 10000000 | AK40: 10000000 | AL40: 10000000 | AM40: 10000000 | AN40: 10000000 | AO40: 10000000 | AP40: 10000000 | AQ40: 10000000 | AR40: 10000000 | AS40: 10000000 | AT40: 10000000 | AU40: 10000000 | AV40: 10000000 | AW40: 10000000 | AX40: 10000000 | AY40: 10000000 | AZ40: 10000000 | BA40: 10000000 | BB40: 10000000 | BC40: 10000000 | BD40: 10000000 | BE40: 10000000 | BF40: 10000000 | BG40: 10000000 | BH40: 10000000 | BI40: 10000000 | BJ40: 10000000 | BK40: 10000000
B41: Total Circulating Supply (Sum) | C41: 1000000000 | D41: 155347224 | E41: 170694443 | F41: 186041667 | G41: 201388890 | H41: 216736110 | I41: 232083333 | J41: 247430557 | K41: 262777776 | L41: 278125000 | M41: 293472224 | N41: 308819443 | O41: 324166667 | P41: 344722223 | Q41: 365277777 | R41: 385833333 | S41: 406388890 | T41: 426944443 | U41: 447500000 | V41: 468055557 | W41: 488611110 | X41: 509166667 | Y41: 529722223 | Z41: 550277777 | AA41: 570833333 | AB41: 590972223 | AC41: 611111110 | AD41: 631250000 | AE41: 651388890 | AF41: 671527777 | AG41: 691666667 | AH41: 711805556 | AI41: 731944444 | AJ41: 752083333 | AK41: 772222223 | AL41: 792361110 | AM41: 812500000 | AN41: 822916667 | AO41: 833333333 | AP41: 843750000 | AQ41: 854166667 | AR41: 864583333 | AS41: 875000000 | AT41: 885416667 | AU41: 895833333 | AV41: 906250000 | AW41: 916666667 | AX41: 927083333 | AY41: 937500000 | AZ41: 942708333 | BA41: 947916667 | BB41: 953125000 | BC41: 958333333 | BD41: 963541667 | BE41: 968750000 | BF41: 973958333 | BG41: 979166667 | BH41: 984375000 | BI41: 989583333 | BJ41: 994791667 | BK41: 1000000000
C42: =+B34 -> Founders, Team & Partners | D42: =+D34 -> 0 | E42: =+E34 -> 0 | F42: =+F34 -> 0 | G42: =+G34 -> 0 | H42: =+H34 -> 0 | I42: =+I34 -> 0 | J42: =+J34 -> 0 | K42: =+K34 -> 0 | ... BK42: =+BK34 -> 250000000
C43: =+B35 -> Key Partnerships & Projects | D43: =+D35 -> 4166667 | E43: =+E35 -> 8333333 | F43: =+F35 -> 12500000 | G43: =+G35 -> 16666667 | H43: =+H35 -> 20833333 | I43: =+I35 -> 25000000 | J43: =+J35 -> 29166667 | K43: =+K35 -> 33333333 | ... BK43: =+BK35 -> 200000000
C44: =+B36 -> Ecosystem & Web3 Platform | D44: =+D36 -> 5555556 | E44: =+E36 -> 11111111 | F44: =+F36 -> 16666667 | G44: =+G36 -> 22222222 | H44: =+H36 -> 27777778 | I44: =+I36 -> 33333333 | J44: =+J36 -> 38888889 | K44: =+K36 -> 44444444 | ... BK44: =+BK36 -> 200000000
C45: =+B37 -> Marketing & Community Growth | D45: =+D37 -> 4166667 | E45: =+E37 -> 8333333 | F45: =+F37 -> 12500000 | G45: =+G37 -> 16666667 | H45: =+H37 -> 20833333 | I45: =+I37 -> 25000000 | J45: =+J37 -> 29166667 | K45: =+K37 -> 33333333 | ... BK45: =+BK37 -> 150000000
C46: =+B38 -> Treasury & Reserve | D46: =+D38 -> 140000000 | E46: =+E38 -> 140000000 | F46: =+F38 -> 140000000 | G46: =+G38 -> 140000000 | H46: =+H38 -> 140000000 | I46: =+I38 -> 140000000 | J46: =+J38 -> 140000000 | K46: =+K38 -> 140000000 | ... BK46: =+BK38 -> 140000000
C47: =+B39 -> Staking Rewards | D47: =+D39 -> 1041667 | E47: =+E39 -> 2083333 | F47: =+F39 -> 3125000 | G47: =+G39 -> 4166667 | H47: =+H39 -> 5208333 | I47: =+I39 -> 6250000 | J47: =+J39 -> 7291667 | K47: =+K39 -> 8333333 | ... BK47: =+BK39 -> 50000000
C48: =+B40 -> Charitable Initiatives | D48: =+D40 -> 416667 | E48: =+E40 -> 833333 | F48: =+F40 -> 1250000 | G48: =+G40 -> 1666667 | H48: =+H40 -> 2083333 | I48: =+I40 -> 2500000 | J48: =+J40 -> 2916667 | K48: =+K40 -> 3333333 | ... BK48: =+BK40 -> 10000000

Sheet Scenario Analysis
B1: Best Case Scenario
B2: Income Statement | M2: Scenario Analysis
B3: For the Financial years | M3: Percentage Change | N3: 0.5
D4: Year 1 | E4: Year 2 | F4: Year 3 | G4: Year 4 | H4: Year 5
B5: Revenue | D5: =PL!D10*(1+'Scenario Analysis'!$N$3) -> 13568623 | E5: =PL!E10*(1+'Scenario Analysis'!$N$3) -> 76428727 | F5: =PL!F10*(1+'Scenario Analysis'!$N$3) -> 1.6755912e+08 | G5: =PL!G10*(1+'Scenario Analysis'!$N$3) -> 2.0390913e+08 | H5: =PL!H10*(1+'Scenario Analysis'!$N$3) -> 2.4341008e+08
B6: Cost of goods sold | D6: =PL!D16*(1+$N$3) -> 2574150.7 | E6: =PL!E16*(1+$N$3) -> 26973493 | F6: =PL!F16*(1+$N$3) -> 65841695 | G6: =PL!G16*(1+$N$3) -> 80461832 | H6: =PL!H16*(1+$N$3) -> 96611507
B7: Gross profit | D7: =D5-D6 -> 10994473 | E7: =E5-E6 -> 49455234 | F7: =F5-F6 -> 1.0171743e+08 | G7: =G5-G6 -> 1.234473e+08 | H7: =H5-H6 -> 1.4679858e+08
B8: Operating expenses | D8: =+PL!D47 -> 4800000 | E8: =+PL!E47 -> 6396720 | F8: =+PL!F47 -> 8340772 | G8: =+PL!G47 -> 12044485 | H8: =+PL!H47 -> 14714498
B9: EBITDA | D9: =D7-D8 -> 6194472.8 | E9: =E7-E8 -> 43058514 | F9: =F7-F8 -> 93376657 | G9: =G7-G8 -> 1.1140282e+08 | H9: =H7-H8 -> 1.3208408e+08
C10: Depreciation and Amortisation expense | D10: =+PL!D50 -> 24866.087 | E10: =+PL!E50 -> 87018.997 | F10: =+PL!F50 -> 126929.23 | G10: =+PL!G50 -> 140793.93 | H10: =+PL!H50 -> 132568.89
C11: Interest expense | D11: =+PL!D53 -> 0 | E11: =+PL!E53 -> 0 | F11: =+PL!F53 -> 0 | G11: =+PL!G53 -> 0 | H11: =+PL!H53 -> 0
B12: Earnings (loss) before taxes | D12: =D9-D10-D11 -> 6169606.7 | E12: =E9-E10-E11 -> 42971495 | F12: =F9-F10-F11 -> 93249728 | G12: =G9-G10-G11 -> 1.1126202e+08 | H12: =H9-H10-H11 -> 1.3195151e+08
B16: Worst Case Scenario | M16: Scenario Analysis
B17: Income Statement | M17: Percentage Change | N17: 0.5
B18: For the Financial years
D19: Year 1 | E19: Year 2 | F19: Year 3 | G19: Year 4 | H19: Year 5
B20: Revenue | D20: =PL!D10*(1-'Scenario Analysis'!$N$17) -> 4522874.5 | E20: =PL!E10*(1-'Scenario Analysis'!$N$17) -> 25476242 | F20: =PL!F10*(1-'Scenario Analysis'!$N$17) -> 55853041 | G20: =PL!G10*(1-'Scenario Analysis'!$N$17) -> 67969711 | H20: =PL!H10*(1-'Scenario Analysis'!$N$17) -> 81136694
B21: Cost of goods sold | D21: =PL!D16*(1-$N$17) -> 858050.22 | E21: =PL!E16*(1-$N$17) -> 8991164.4 | F21: =PL!F16*(1-$N$17) -> 21947232 | G21: =PL!G16*(1-$N$17) -> 26820611 | H21: =PL!H16*(1-$N$17) -> 32203836
B22: Gross profit | D22: =D20-D21 -> 3664824.3 | E22: =E20-E21 -> 16485078 | F22: =F20-F21 -> 33905810 | G22: =G20-G21 -> 41149101 | H22: =H20-H21 -> 48932859
B23: Operating expenses | D23: =D8 -> 4800000 | E23: =E8 -> 6396720 | F23: =F8 -> 8340772 | G23: =G8 -> 12044485 | H23: =H8 -> 14714498
B24: EBITDA | D24: =D22-D23 -> -1135175.7 | E24: =E22-E23 -> 10088358 | F24: =F22-F23 -> 25565038 | G24: =G22-G23 -> 29104616 | H24: =H22-H23 -> 34218361
C25: Depreciation and Amortisation expense | D25: =+D10 -> 24866.087 | E25: =+E10 -> 87018.997 | F25: =+F10 -> 126929.23 | G25: =+G10 -> 140793.93 | H25: =+H10 -> 132568.89
C26: Interest expense | D26: =+D11 -> 0 | E26: =+E11 -> 0 | F26: =+F11 -> 0 | G26: =+G11 -> 0 | H26: =+H11 -> 0
B27: Earnings (loss) before taxes | D27: =D24-D25-D26 -> -1160041.8 | E27: =E24-E25-E26 -> 10001339 | F27: =F24-F25-F26 -> 25438108 | G27: =G24-G25-G26 -> 28963822 | H27: =H24-H25-H26 -> 34085792

Sheet PL
A1: =+'Loan Amortization'!A1:C1 -> Projected Financials - AKH Digital
B3: STATEMENT OF PROFIT & LOSS
B4: FOR THE YEAR ENDED
D5: FY | E5: FY | F5: FY | G5: FY | H5: FY
D6: ='Hiring Plan'!I4 -> 1 | E6: ='Hiring Plan'!J4 -> 2 | F6: ='Hiring Plan'!K4 -> 3 | G6: ='Hiring Plan'!L4 -> 4 | H6: ='Hiring Plan'!M4 -> 5
D7: =+'Revenue Summary'!D4 -> 2026 | E7: =+'Revenue Summary'!E4 -> 2027 | F7: =+'Revenue Summary'!F4 -> 2028 | G7: =+'Revenue Summary'!G4 -> 2029 | H7: =+'Revenue Summary'!H4 -> 2030
B8: Income
B10: =B66 -> Gross Revenue | D10: =SUMIF($D$62:$BK$62,D$6,$D66:$BK66) -> 9045749 | E10: =SUMIF($D$62:$BK$62,E$6,$D66:$BK66) -> 50952485 | F10: =SUMIF($D$62:$BK$62,F$6,$D66:$BK66) -> 1.1170608e+08 | G10: =SUMIF($D$62:$BK$62,G$6,$D66:$BK66) -> 1.3593942e+08 | H10: =SUMIF($D$62:$BK$62,H$6,$D66:$BK66) -> 1.6227339e+08
B11: =B67 -> Gross Revenue | D11: =SUM(D10) -> 9045749 | E11: =SUM(E10) -> 50952485 | F11: =SUM(F10) -> 1.1170608e+08 | G11: =SUM(G10) -> 1.3593942e+08 | H11: =SUM(H10) -> 1.6227339e+08
B12: =B68 -> Cost of Sale
B14: =+B70 -> Cost of Sales | D14: =SUMIF($D$62:$BK$62,D$6,$D70:$BK70) -> 1716100.4 | E14: =SUMIF($D$62:$BK$62,E$6,$D70:$BK70) -> 17982329 | F14: =SUMIF($D$62:$BK$62,F$6,$D70:$BK70) -> 43894463 | G14: =SUMIF($D$62:$BK$62,G$6,$D70:$BK70) -> 53641221 | H14: =SUMIF($D$62:$BK$62,H$6,$D70:$BK70) -> 64407672
B16: =B73 -> Total Cost of Goods Sold | D16: =SUM(D13:D15) -> 1716100.4 | E16: =SUM(E13:E15) -> 17982329 | F16: =SUM(F13:F15) -> 43894463 | G16: =SUM(G13:G15) -> 53641221 | H16: =SUM(H13:H15) -> 64407672
B18: =B75 -> Gross Profit | D18: =D11-D16 -> 7329648.6 | E18: =E11-E16 -> 32970156 | F18: =F11-F16 -> 67811619 | G18: =G11-G16 -> 82298202 | H18: =H11-H16 -> 97865717
D19: =D18/D11 -> 0.81028653 | E19: =E18/E11 -> 0.64707651 | F19: =F18/F11 -> 0.60705396 | G19: =G18/G11 -> 0.60540349 | H19: =H18/H11 -> 0.6030916
B20: =B77 -> Expenses
B21: =B78 -> Salary | D21: =SUMIF($D$62:$BK$62,D$6,$D78:$BK78) -> 2892000 | E21: =SUMIF($D$62:$BK$62,E$6,$D78:$BK78) -> 4297920 | F21: =SUMIF($D$62:$BK$62,F$6,$D78:$BK78) -> 6032092 | G21: =SUMIF($D$62:$BK$62,G$6,$D78:$BK78) -> 9504937.2 | H21: =SUMIF($D$62:$BK$62,H$6,$D78:$BK78) -> 11920995
B22: =B79 -> Hosting / Cloud Services | D22: =SUMIF($D$62:$BK$62,D$6,$D79:$BK79) -> 300000 | E22: =SUMIF($D$62:$BK$62,E$6,$D79:$BK79) -> 330000 | F22: =SUMIF($D$62:$BK$62,F$6,$D79:$BK79) -> 363000 | G22: =SUMIF($D$62:$BK$62,G$6,$D79:$BK79) -> 399300 | H22: =SUMIF($D$62:$BK$62,H$6,$D79:$BK79) -> 439230
B23: =B80 -> Security / DevOps Tools | D23: =SUMIF($D$62:$BK$62,D$6,$D80:$BK80) -> 120000 | E23: =SUMIF($D$62:$BK$62,E$6,$D80:$BK80) -> 132000 | F23: =SUMIF($D$62:$BK$62,F$6,$D80:$BK80) -> 145200 | G23: =SUMIF($D$62:$BK$62,G$6,$D80:$BK80) -> 159720 | H23: =SUMIF($D$62:$BK$62,H$6,$D80:$BK80) -> 175692
B24: =B81 -> Data & API Services | D24: =SUMIF($D$62:$BK$62,D$6,$D81:$BK81) -> 60000 | E24: =SUMIF($D$62:$BK$62,E$6,$D81:$BK81) -> 66000 | F24: =SUMIF($D$62:$BK$62,F$6,$D81:$BK81) -> 72600 | G24: =SUMIF($D$62:$BK$62,G$6,$D81:$BK81) -> 79860 | H24: =SUMIF($D$62:$BK$62,H$6,$D81:$BK81) -> 87846
B25: =B82 -> Software Subscriptions | D25: =SUMIF($D$62:$BK$62,D$6,$D82:$BK82) -> 84000 | E25: =SUMIF($D$62:$BK$62,E$6,$D82:$BK82) -> 92400 | F25: =SUMIF($D$62:$BK$62,F$6,$D82:$BK82) -> 101640 | G25: =SUMIF($D$62:$BK$62,G$6,$D82:$BK82) -> 111804 | H25: =SUMIF($D$62:$BK$62,H$6,$D82:$BK82) -> 122984.4
B26: =B83 -> Hardware / Equipment | D26: =SUMIF($D$62:$BK$62,D$6,$D83:$BK83) -> 36000 | E26: =SUMIF($D$62:$BK$62,E$6,$D83:$BK83) -> 39600 | F26: =SUMIF($D$62:$BK$62,F$6,$D83:$BK83) -> 43560 | G26: =SUMIF($D$62:$BK$62,G$6,$D83:$BK83) -> 47916 | H26: =SUMIF($D$62:$BK$62,H$6,$D83:$BK83) -> 52707.6
B27: =B84 -> Paid Digital Ads | D27: =SUMIF($D$62:$BK$62,D$6,$D84:$BK84) -> 240000 | E27: =SUMIF($D$62:$BK$62,E$6,$D84:$BK84) -> 264000 | F27: =SUMIF($D$62:$BK$62,F$6,$D84:$BK84) -> 290400 | G27: =SUMIF($D$62:$BK$62,G$6,$D84:$BK84) -> 319440 | H27: =SUMIF($D$62:$BK$62,H$6,$D84:$BK84) -> 351384
B28: =B85 -> Community & Influencer Marketing | D28: =SUMIF($D$62:$BK$62,D$6,$D85:$BK85) -> 120000 | E28: =SUMIF($D$62:$BK$62,E$6,$D85:$BK85) -> 132000 | F28: =SUMIF($D$62:$BK$62,F$6,$D85:$BK85) -> 145200 | G28: =SUMIF($D$62:$BK$62,G$6,$D85:$BK85) -> 159720 | H28: =SUMIF($D$62:$BK$62,H$6,$D85:$BK85) -> 175692
B29: =B86 -> Content & PR | D29: =SUMIF($D$62:$BK$62,D$6,$D86:$BK86) -> 60000 | E29: =SUMIF($D$62:$BK$62,E$6,$D86:$BK86) -> 66000 | F29: =SUMIF($D$62:$BK$62,F$6,$D86:$BK86) -> 72600 | G29: =SUMIF($D$62:$BK$62,G$6,$D86:$BK86) -> 79860 | H29: =SUMIF($D$62:$BK$62,H$6,$D86:$BK86) -> 87846
B30: =B87 -> Partnerships / Conferences | D30: =SUMIF($D$62:$BK$62,D$6,$D87:$BK87) -> 60000 | E30: =SUMIF($D$62:$BK$62,E$6,$D87:$BK87) -> 66000 | F30: =SUMIF($D$62:$BK$62,F$6,$D87:$BK87) -> 72600 | G30: =SUMIF($D$62:$BK$62,G$6,$D87:$BK87) -> 79860 | H30: =SUMIF($D$62:$BK$62,H$6,$D87:$BK87) -> 87846
B31: =B88 -> FCA & Regulatory Fees | D31: =SUMIF($D$62:$BK$62,D$6,$D88:$BK88) -> 96000 | E31: =SUMIF($D$62:$BK$62,E$6,$D88:$BK88) -> 105600 | F31: =SUMIF($D$62:$BK$62,F$6,$D88:$BK88) -> 116160 | G31: =SUMIF($D$62:$BK$62,G$6,$D88:$BK88) -> 127776 | H31: =SUMIF($D$62:$BK$62,H$6,$D88:$BK88) -> 140553.6
B32: =B89 -> Legal Counsel (Retainer) | D32: =SUMIF($D$62:$BK$62,D$6,$D89:$BK89) -> 84000 | E32: =SUMIF($D$62:$BK$62,E$6,$D89:$BK89) -> 92400 | F32: =SUMIF($D$62:$BK$62,F$6,$D89:$BK89) -> 101640 | G32: =SUMIF($D$62:$BK$62,G$6,$D89:$BK89) -> 111804 | H32: =SUMIF($D$62:$BK$62,H$6,$D89:$BK89) -> 122984.4
... B45: =B102 -> >>>Placeholder<<< | D45: =SUMIF($D$62:$BK$62,D$6,$D102:$BK102) -> 0 | E45: =SUMIF($D$62:$BK$62,E$6,$D102:$BK102) -> 0 | F45: =SUMIF($D$62:$BK$62,F$6,$D102:$BK102) -> 0 | G45: =SUMIF($D$62:$BK$62,G$6,$D102:$BK102) -> 0 | H45: =SUMIF($D$62:$BK$62,H$6,$D102:$BK102) -> 0
B47: =B104 -> Total Operating Expenses | D47: =SUM(D21:D45) -> 4800000 | E47: =SUM(E21:E45) -> 6396720 | F47: =SUM(F21:F45) -> 8340772 | G47: =SUM(G21:G45) -> 12044485 | H47: =SUM(H21:H45) -> 14714498
B48: =B105 -> Operating Income | D48: =D18-D47 -> 2529648.6 | E48: =E18-E47 -> 26573436 | F48: =F18-F47 -> 59470847 | G48: =G18-G47 -> 70253716 | H48: =H18-H47 -> 83151220
D49: =D48/D11 -> 0.27965054 | E49: =E48/E11 -> 0.52153366 | F49: =F48/F11 -> 0.53238683 | G49: =G48/G11 -> 0.51680164 | H49: =H48/H11 -> 0.51241439
B50: =B107 -> Depreciation | D50: =SUMIF($D$62:$BK$62,D$6,$D107:$BK107) -> 24866.087 | E50: =SUMIF($D$62:$BK$62,E$6,$D107:$BK107) -> 87018.997 | F50: =SUMIF($D$62:$BK$62,F$6,$D107:$BK107) -> 126929.23 | G50: =SUMIF($D$62:$BK$62,G$6,$D107:$BK107) -> 140793.93 | H50: =SUMIF($D$62:$BK$62,H$6,$D107:$BK107) -> 132568.89
B51: =B108 -> EBIT | D51: =D48-D50 -> 2504782.5 | E51: =E48-E50 -> 26486417 | F51: =F48-F50 -> 59343918 | G51: =G48-G50 -> 70112922 | H51: =H48-H50 -> 83018651
B53: =B110 -> Interest | D53: =SUMIF($D$62:$BK$62,D$6,$D110:$BK110) -> 0 | E53: =SUMIF($D$62:$BK$62,E$6,$D110:$BK110) -> 0 | F53: =SUMIF($D$62:$BK$62,F$6,$D110:$BK110) -> 0 | G53: =SUMIF($D$62:$BK$62,G$6,$D110:$BK110) -> 0 | H53: =SUMIF($D$62:$BK$62,H$6,$D110:$BK110) -> 0
B54: =B111 -> EBT | D54: =D51-D52 -> 2504782.5 | E54: =E51-E52 -> 26486417 | F54: =F51-F52 -> 59343918 | G54: =G51-G52 -> 70112922 | H54: =H51-H52 -> 83018651
B56: =B113 -> Corporate Tax | D56: =SUMIF($D$62:$BK$62,D$6,$D113:$BK113) -> 636843.91 | E56: =SUMIF($D$62:$BK$62,E$6,$D113:$BK113) -> 5297283.4 | F56: =SUMIF($D$62:$BK$62,F$6,$D113:$BK113) -> 11868784 | G56: =SUMIF($D$62:$BK$62,G$6,$D113:$BK113) -> 14022584 | H56: =SUMIF($D$62:$BK$62,H$6,$D113:$BK113) -> 16603730
A57: =AVERAGE(D114:BK114) -> 3217291.1 | B57: =B114 -> Net profit | D57: =D54-D56 -> 1867938.6 | E57: =E54-E56 -> 21189134 | F57: =F54-F56 -> 47475135 | G57: =G54-G56 -> 56090338 | H57: =H54-H56 -> 66414921
D61: =YEAR(D63) -> 2026 | E61: =YEAR(E63) -> 2026 | F61: =YEAR(F63) -> 2026 | G61: =YEAR(G63) -> 2026 | H61: =YEAR(H63) -> 2026 | I61: =YEAR(I63) -> 2026 | J61: =YEAR(J63) -> 2026 | K61: =YEAR(K63) -> 2027 | ... BK61: =YEAR(BK63) -> 2031
D62: 1 | E62: =+D62 -> 1 | F62: =+E62 -> 1 | G62: =+F62 -> 1 | H62: =+G62 -> 1 | I62: =+H62 -> 1 | J62: =+I62 -> 1 | K62: =+J62 -> 1 | L62: =+K62 -> 1 | ... O62: =+N62 -> 1 | P62: =+O62+1 -> 2 | Q62: =+P62 -> 2 | R62: =+Q62 -> 2 | S62: =+R62 -> 2 | T62: =+S62 -> 2 | U62: =+T62 -> 2 | V62: =+U62 -> 2 | W62: =+V62 -> 2 | X62: =+W62 -> 2 | ... AA62: =+Z62 -> 2 | AB62: =+AA62+1 -> 3 | AC62: =+AB62 -> 3 | AD62: =+AC62 -> 3 | AE62: =+AD62 -> 3 | AF62: =+AE62 -> 3 | AG62: =+AF62 -> 3 | AH62: =+AG62 -> 3 | AI62: =+AH62 -> 3 | AJ62: =+AI62 -> 3 | ... AM62: =+AL62 -> 3 | AN62: =+AM62+1 -> 4 | AO62: =+AN62 -> 4 | AP62: =+AO62 -> 4 | AQ62: =+AP62 -> 4 | AR62: =+AQ62 -> 4 | AS62: =+AR62 -> 4 | AT62: =+AS62 -> 4 | AU62: =+AT62 -> 4 | AV62: =+AU62 -> 4 | ... AY62: =+AX62 -> 4 | AZ62: =+AY62+1 -> 5 | BA62: =+AZ62 -> 5 | BB62: =+BA62 -> 5 | BC62: =+BB62 -> 5 | BD62: =+BC62 -> 5 | BE62: =+BD62 -> 5 | BF62: =+BE62 -> 5 | BG62: =+BF62 -> 5 | BH62: =+BG62 -> 5 | ... BK62: =+BJ62 -> 5
D63: ='Hiring Plan'!I32 -> 46174 | E63: ='Hiring Plan'!J32 -> 46234 | F63: ='Hiring Plan'!K32 -> 46265 | G63: ='Hiring Plan'!L32 -> 46295 | H63: ='Hiring Plan'!M32 -> 46326 | I63: ='Hiring Plan'!N32 -> 46356 | J63: ='Hiring Plan'!O32 -> 46387 | K63: ='Hiring Plan'!P32 -> 46418 | ... BK63: ='Hiring Plan'!BP32 -> 47999
B64: Income
B66: Gross Revenue | D66: =+'Revenue Summary'!D68 -> 260000 | E66: =+'Revenue Summary'!E68 -> 263000 | F66: =+'Revenue Summary'!F68 -> 267500 | G66: =+'Revenue Summary'!G68 -> 772040 | H66: =+'Revenue Summary'!H68 -> 786620 | I66: =+'Revenue Summary'!I68 -> 801440.8 | J66: =+'Revenue Summary'!J68 -> 816507.2 | K66: =+'Revenue Summary'!K68 -> 832836.62 | ... BK66: =+'Revenue Summary'!BK68 -> 14626680
B67: Gross Revenue | D67: =SUM(D66) -> 260000 | E67: =SUM(E66) -> 263000 | F67: =SUM(F66) -> 267500 | G67: =SUM(G66) -> 772040 | H67: =SUM(H66) -> 786620 | I67: =SUM(I66) -> 801440.8 | J67: =SUM(J66) -> 816507.2 | K67: =SUM(K66) -> 832836.62 | ... BK67: =SUM(BK66) -> 14626680
B68: Cost of Sale
B70: Cost of Sales | D70: =+COS!D87 -> 89000 | E70: =+COS!E87 -> 89660 | F70: =+COS!F87 -> 90320 | G70: =+COS!G87 -> 115993.2 | H70: =+COS!H87 -> 122779.6 | I70: =+COS!I87 -> 128189.46 | J70: =+COS!J87 -> 132223.26 | K70: =+COS!K87 -> 134038.33 | ... BK70: =+COS!BK87 -> 5822557
B73: Total Cost of Goods Sold | D73: =SUM(D69:D72) -> 89000 | E73: =SUM(E69:E72) -> 89660 | F73: =SUM(F69:F72) -> 90320 | G73: =SUM(G69:G72) -> 115993.2 | H73: =SUM(H69:H72) -> 122779.6 | I73: =SUM(I69:I72) -> 128189.46 | J73: =SUM(J69:J72) -> 132223.26 | K73: =SUM(K69:K72) -> 134038.33 | ... BK73: =SUM(BK69:BK72) -> 5822557
B75: Gross Profit | D75: =D67-D73 -> 171000 | E75: =E67-E73 -> 173340 | F75: =F67-F73 -> 177180 | G75: =G67-G73 -> 656046.8 | H75: =H67-H73 -> 663840.4 | I75: =I67-I73 -> 673251.34 | J75: =J67-J73 -> 684283.94 | K75: =K67-K73 -> 698798.29 | ... BK75: =BK67-BK73 -> 8804122.5
D76: =D75/D67 -> 0.65769231 | E76: =E75/E67 -> 0.65908745 | F76: =F75/F67 -> 0.66235514 | G76: =G75/G67 -> 0.84975753 | H76: =H75/H67 -> 0.84391498 | I76: =I75/I67 -> 0.84005124 | J76: =J75/J67 -> 0.83806235 | K76: =K75/K67 -> 0.83905808 | ... BK76: =BK75/BK67 -> 0.60192216
B77: Expenses
B78: Salary | D78: ='Hiring Plan'!I54 -> 241000 | E78: ='Hiring Plan'!J54 -> 241000 | F78: ='Hiring Plan'!K54 -> 241000 | G78: ='Hiring Plan'!L54 -> 241000 | H78: ='Hiring Plan'!M54 -> 241000 | I78: ='Hiring Plan'!N54 -> 241000 | J78: ='Hiring Plan'!O54 -> 241000 | K78: ='Hiring Plan'!P54 -> 241000 | ... BK78: ='Hiring Plan'!BP54 -> 1000126.7
B79: =OPEX!B41 -> Hosting / Cloud Services | D79: =OPEX!D41 -> 25000 | E79: =OPEX!E41 -> 25000 | F79: =OPEX!F41 -> 25000 | G79: =OPEX!G41 -> 25000 | H79: =OPEX!H41 -> 25000 | I79: =OPEX!I41 -> 25000 | J79: =OPEX!J41 -> 25000 | K79: =OPEX!K41 -> 25000 | ... BK79: =OPEX!BK41 -> 36602.5
B80: =OPEX!B42 -> Security / DevOps Tools | D80: =OPEX!D42 -> 10000 | E80: =OPEX!E42 -> 10000 | F80: =OPEX!F42 -> 10000 | G80: =OPEX!G42 -> 10000 | H80: =OPEX!H42 -> 10000 | I80: =OPEX!I42 -> 10000 | J80: =OPEX!J42 -> 10000 | K80: =OPEX!K42 -> 10000 | ... BK80: =OPEX!BK42 -> 14641
B81: =OPEX!B43 -> Data & API Services | D81: =OPEX!D43 -> 5000 | E81: =OPEX!E43 -> 5000 | F81: =OPEX!F43 -> 5000 | G81: =OPEX!G43 -> 5000 | H81: =OPEX!H43 -> 5000 | I81: =OPEX!I43 -> 5000 | J81: =OPEX!J43 -> 5000 | K81: =OPEX!K43 -> 5000 | ... BK81: =OPEX!BK43 -> 7320.5
B82: =OPEX!B44 -> Software Subscriptions | D82: =OPEX!D44 -> 7000 | E82: =OPEX!E44 -> 7000 | F82: =OPEX!F44 -> 7000 | G82: =OPEX!G44 -> 7000 | H82: =OPEX!H44 -> 7000 | I82: =OPEX!I44 -> 7000 | J82: =OPEX!J44 -> 7000 | K82: =OPEX!K44 -> 7000 | ... BK82: =OPEX!BK44 -> 10248.7
B83: =OPEX!B45 -> Hardware / Equipment | D83: =OPEX!D45 -> 3000 | E83: =OPEX!E45 -> 3000 | F83: =OPEX!F45 -> 3000 | G83: =OPEX!G45 -> 3000 | H83: =OPEX!H45 -> 3000 | I83: =OPEX!I45 -> 3000 | J83: =OPEX!J45 -> 3000 | K83: =OPEX!K45 -> 3000 | ... BK83: =OPEX!BK45 -> 4392.3
B84: =OPEX!B46 -> Paid Digital Ads | D84: =OPEX!D46 -> 20000 | E84: =OPEX!E46 -> 20000 | F84: =OPEX!F46 -> 20000 | G84: =OPEX!G46 -> 20000 | H84: =OPEX!H46 -> 20000 | I84: =OPEX!I46 -> 20000 | J84: =OPEX!J46 -> 20000 | K84: =OPEX!K46 -> 20000 | ... BK84: =OPEX!BK46 -> 29282
B85: =OPEX!B47 -> Community & Influencer Marketing | D85: =OPEX!D47 -> 10000 | E85: =OPEX!E47 -> 10000 | F85: =OPEX!F47 -> 10000 | G85: =OPEX!G47 -> 10000 | H85: =OPEX!H47 -> 10000 | I85: =OPEX!I47 -> 10000 | J85: =OPEX!J47 -> 10000 | K85: =OPEX!K47 -> 10000 | ... BK85: =OPEX!BK47 -> 14641
B86: =OPEX!B48 -> Content & PR | D86: =OPEX!D48 -> 5000 | E86: =OPEX!E48 -> 5000 | F86: =OPEX!F48 -> 5000 | G86: =OPEX!G48 -> 5000 | H86: =OPEX!H48 -> 5000 | I86: =OPEX!I48 -> 5000 | J86: =OPEX!J48 -> 5000 | K86: =OPEX!K48 -> 5000 | ... BK86: =OPEX!BK48 -> 7320.5
B87: =OPEX!B49 -> Partnerships / Conferences | D87: =OPEX!D49 -> 5000 | E87: =OPEX!E49 -> 5000 | F87: =OPEX!F49 -> 5000 | G87: =OPEX!G49 -> 5000 | H87: =OPEX!H49 -> 5000 | I87: =OPEX!I49 -> 5000 | J87: =OPEX!J49 -> 5000 | K87: =OPEX!K49 -> 5000 | ... BK87: =OPEX!BK49 -> 7320.5
B88: =OPEX!B50 -> FCA & Regulatory Fees | D88: =OPEX!D50 -> 8000 | E88: =OPEX!E50 -> 8000 | F88: =OPEX!F50 -> 8000 | G88: =OPEX!G50 -> 8000 | H88: =OPEX!H50 -> 8000 | I88: =OPEX!I50 -> 8000 | J88: =OPEX!J50 -> 8000 | K88: =OPEX!K50 -> 8000 | ... BK88: =OPEX!BK50 -> 11712.8
B89: =OPEX!B51 -> Legal Counsel (Retainer) | D89: =OPEX!D51 -> 7000 | E89: =OPEX!E51 -> 7000 | F89: =OPEX!F51 -> 7000 | G89: =OPEX!G51 -> 7000 | H89: =OPEX!H51 -> 7000 | I89: =OPEX!I51 -> 7000 | J89: =OPEX!J51 -> 7000 | K89: =OPEX!K51 -> 7000 | ... BK89: =OPEX!BK51 -> 10248.7
B90: =OPEX!B52 -> External Audit / Accounting | D90: =OPEX!D52 -> 5000 | E90: =OPEX!E52 -> 5000 | F90: =OPEX!F52 -> 5000 | G90: =OPEX!G52 -> 5000 | H90: =OPEX!H52 -> 5000 | I90: =OPEX!I52 -> 5000 | J90: =OPEX!J52 -> 5000 | K90: =OPEX!K52 -> 5000 | ... BK90: =OPEX!BK52 -> 7320.5
... B102: =OPEX!B64 -> >>>Placeholder<<< | D102: =OPEX!D64 -> 0 | E102: =OPEX!E64 -> 0 | F102: =OPEX!F64 -> 0 | G102: =OPEX!G64 -> 0 | H102: =OPEX!H64 -> 0 | I102: =OPEX!I64 -> 0 | J102: =OPEX!J64 -> 0 | K102: =OPEX!K64 -> 0 | ... BK102: =OPEX!BK64 -> 0
B104: Total Operating Expenses | D104: =SUM(D78:D102) -> 400000 | E104: =SUM(E78:E102) -> 400000 | F104: =SUM(F78:F102) -> 400000 | G104: =SUM(G78:G102) -> 400000 | H104: =SUM(H78:H102) -> 400000 | I104: =SUM(I78:I102) -> 400000 | J104: =SUM(J78:J102) -> 400000 | K104: =SUM(K78:K102) -> 400000 | ... BK104: =SUM(BK78:BK102) -> 1232918.6
B105: Operating Income | D105: =D75-D104 -> -229000 | E105: =E75-E104 -> -226660 | F105: =F75-F104 -> -222820 | G105: =G75-G104 -> 256046.8 | H105: =H75-H104 -> 263840.4 | I105: =I75-I104 -> 273251.34 | J105: =J75-J104 -> 284283.94 | K105: =K75-K104 -> 298798.29 | ... BK105: =BK75-BK104 -> 7571203.9
D106: =D105/D67 -> -0.88076923 | E106: =E105/E67 -> -0.8618251 | F106: =F105/F67 -> -0.83297196 | G106: =G105/G67 -> 0.33164966 | H106: =H105/H67 -> 0.33541024 | I106: =I105/I67 -> 0.34095012 | J106: =J105/J67 -> 0.34817077 | K106: =K105/K67 -> 0.3587718 | ... BK106: =BK105/BK67 -> 0.51762971
B107: Depreciation | D107: =+CAPEX!D41 -> 0 | E107: =+CAPEX!E41 -> 290 | F107: =+CAPEX!F41 -> 667.1 | G107: =+CAPEX!G41 -> 1040.429 | H107: =+CAPEX!H41 -> 1410.0247 | I107: =+CAPEX!I41 -> 1775.9245 | J107: =+CAPEX!J41 -> 2048.1652 | K107: =+CAPEX!K41 -> 2547.6836 | ... BK107: =+CAPEX!BK41 -> 10756.797
B108: EBIT | D108: =D105-D107 -> -229000 | E108: =E105-E107 -> -226950 | F108: =F105-F107 -> -223487.1 | G108: =G105-G107 -> 255006.37 | H108: =H105-H107 -> 262430.38 | I108: =I105-I107 -> 271475.41 | J108: =J105-J107 -> 282235.78 | K108: =K105-K107 -> 296250.61 | ... BK108: =BK105-BK107 -> 7560447.1
B110: Interest | D110: {=TRANSPOSE('Loan Amortization'!F13:F72)} -> 0 | E110: 0 | F110: 0 | G110: 0 | H110: 0 | I110: 0 | J110: 0 | K110: 0 | L110: 0 | M110: 0 | N110: 0 | O110: 0 | P110: 0 | Q110: 0 | R110: 0 | S110: 0 | T110: 0 | U110: 0 | V110: 0 | W110: 0 | X110: 0 | Y110: 0 | Z110: 0 | AA110: 0 | AB110: 0 | AC110: 0 | AD110: 0 | AE110: 0 | AF110: 0 | AG110: 0 | AH110: 0 | AI110: 0 | AJ110: 0 | AK110: 0 | AL110: 0 | AM110: 0 | AN110: 0 | AO110: 0 | AP110: 0 | AQ110: 0 | AR110: 0 | AS110: 0 | AT110: 0 | AU110: 0 | AV110: 0 | AW110: 0 | AX110: 0 | AY110: 0 | AZ110: 0 | BA110: 0 | BB110: 0 | BC110: 0 | BD110: 0 | BE110: 0 | BF110: 0 | BG110: 0 | BH110: 0 | BI110: 0 | BJ110: 0 | BK110: 0
B111: EBT | D111: =D108-D110 -> -229000 | E111: =E108-E110 -> -226950 | F111: =F108-F110 -> -223487.1 | G111: =G108-G110 -> 255006.37 | H111: =H108-H110 -> 262430.38 | I111: =I108-I110 -> 271475.41 | J111: =J108-J110 -> 282235.78 | K111: =K108-K110 -> 296250.61 | ... BK111: =BK108-BK110 -> 7560447.1
B113: Corporate Tax | D113: =IF(D111>0,D111*'Assumption Sheet'!$D$8,0) -> 0 | E113: =IF(E111>0,E111*'Assumption Sheet'!$D$8,0) -> 0 | F113: =IF(F111>0,F111*'Assumption Sheet'!$D$8,0) -> 0 | G113: =IF(G111>0,G111*'Assumption Sheet'!$D$8,0) -> 51001.274 | H113: =IF(H111>0,H111*'Assumption Sheet'!$D$8,0) -> 52486.075 | I113: =IF(I111>0,I111*'Assumption Sheet'!$D$8,0) -> 54295.082 | J113: =IF(J111>0,J111*'Assumption Sheet'!$D$8,0) -> 56447.156 | K113: =IF(K111>0,K111*'Assumption Sheet'!$D$8,0) -> 59250.121 | ... BK113: =IF(BK111>0,BK111*'Assumption Sheet'!$D$8,0) -> 1512089.4
B114: Net profit | D114: =D111-D113 -> -229000 | E114: =E111-E113 -> -226950 | F114: =F111-F113 -> -223487.1 | G114: =G111-G113 -> 204005.1 | H114: =H111-H113 -> 209944.3 | I114: =I111-I113 -> 217180.33 | J114: =J111-J113 -> 225788.62 | K114: =K111-K113 -> 237000.49 | ... BK114: =BK111-BK113 -> 6048357.7

Sheet BS
A1: =+PL!A1 -> Projected Financials - AKH Digital
B3: STATEMENT OF FINANCIAL POSITION
B4: =PL!B4 -> FOR THE YEAR ENDED
D5: =PL!D5 -> FY | E5: =PL!E5 -> FY | F5: =PL!F5 -> FY | G5: =PL!G5 -> FY | H5: =PL!H5 -> FY
D6: =+PL!D7 -> 2026 | E6: =+PL!E7 -> 2027 | F6: =+PL!F7 -> 2028 | G6: =+PL!G7 -> 2029 | H6: =+PL!H7 -> 2030
B8: Assets
B9: Current Assets
B10: Cash/bank | D10: =O52 -> 2537475.6 | E10: =AA52 -> 22222087 | F10: =AM52 -> 69008099 | G10: =AY52 -> 1.2485053e+08 | H10: =BK52 -> 1.9092868e+08
B11: Reveivable | D11: =O53 -> 222370.13 | E11: =AA53 -> 1292442.8 | F11: =AM53 -> 1693016.7 | G11: =AY53 -> 2008522.6 | H11: =BK53 -> 2404385.7
B12: Inventory | D12: =O54 -> 65753.425 | E12: =AA54 -> 98566.027 | F12: =AM54 -> 143429.75 | G12: =AY54 -> 172213.17 | H12: =BK54 -> 202671.55
B13: Prepaid | D13: =O55 -> 0 | E13: =AA55 -> 0 | F13: =AM55 -> 0 | G13: =AY55 -> 0 | H13: =BK55 -> 0
B15: Total Current Assets | D15: =SUM(D10:D14) -> 2825599.2 | E15: =SUM(E10:E14) -> 23613096 | F15: =SUM(F10:F14) -> 70844546 | G15: =SUM(G10:G14) -> 1.2703126e+08 | H15: =SUM(H10:H14) -> 1.9353574e+08
B16: Non-Current Assets
B17: Fixture | D17: =O59 -> 522000 | E17: =AA59 -> 1038000 | F17: =AM59 -> 1446000 | G17: =AY59 -> 1514400 | H17: =BK59 -> 1582800
B18: Equipment | D18: =O60 -> 0 | E18: =AA60 -> 0 | F18: =AM60 -> 0 | G18: =AY60 -> 0 | H18: =BK60 -> 0
B19: Intangible Assets | D19: =O61 -> 0 | E19: =AA61 -> 0 | F19: =AM61 -> 0 | G19: =AY61 -> 0 | H19: =BK61 -> 0
B20: Acc. Depreciation | D20: =O62 -> 24866.087 | E20: =AA62 -> 111885.08 | F20: =AM62 -> 238814.31 | G20: =AY62 -> 379608.25 | H20: =BK62 -> 512177.13
B22: Total Non-Current Assets | D22: =SUM(D17:D19)-D20 -> 497133.91 | E22: =SUM(E17:E19)-E20 -> 926114.92 | F22: =SUM(F17:F19)-F20 -> 1207185.7 | G22: =SUM(G17:G19)-G20 -> 1134791.8 | H22: =SUM(H17:H19)-H20 -> 1070622.9
B24: Total Assets | D24: =D15+D22 -> 3322733.1 | E24: =E15+E22 -> 24539211 | F24: =F15+F22 -> 72051732 | G24: =G15+G22 -> 1.2816606e+08 | H24: =H15+H22 -> 1.9460636e+08
B26: Equity & Liability
B27: Payable | D27: =O69 -> 54794.521 | E27: =AA69 -> 82138.356 | F27: =AM69 -> 119524.79 | G27: =AY69 -> 143510.97 | H27: =BK69 -> 168892.96
B28: Other Liability | D28: =O70 -> 0 | E28: =AA70 -> 0 | F28: =AM70 -> 0 | G28: =AY70 -> 0 | H28: =BK70 -> 0
B29: Total Current Assets | D29: =SUM(D27:D28) -> 54794.521 | E29: =SUM(E27:E28) -> 82138.356 | F29: =SUM(F27:F28) -> 119524.79 | G29: =SUM(G27:G28) -> 143510.97 | H29: =SUM(H27:H28) -> 168892.96
B30: Long term Loan
B31: Loan | D31: =O73 -> 0 | E31: =AA73 -> 0 | F31: =AM73 -> 0 | G31: =AY73 -> 0 | H31: =BK73 -> 0
B33: Total Liability | D33: =D29+D31 -> 54794.521 | E33: =E29+E31 -> 82138.356 | F33: =F29+F31 -> 119524.79 | G33: =G29+G31 -> 143510.97 | H33: =H29+H31 -> 168892.96
B35: Equity
B36: Share Capital | D36: =O78 -> 1400000 | E36: =AA78 -> 1400000 | F36: =AM78 -> 1400000 | G36: =AY78 -> 1400000 | H36: =BK78 -> 1400000
B37: Retain earning | D37: =O79 -> 1348492.3 | E37: =AA79 -> 19703618 | F37: =AM79 -> 66241296 | G37: =AY79 -> 1.2156366e+08 | H37: =BK79 -> 1.8698911e+08
B38: Current profit | D38: =O80 -> 519446.25 | E38: =AA80 -> 3353453.8 | F38: =AM80 -> 4290910.3 | G38: =AY80 -> 5058888.6 | H38: =BK80 -> 6048357.7
B39: Total Equity | D39: =SUM(D36:D38) -> 3267938.6 | E39: =SUM(E36:E38) -> 24457072 | F39: =SUM(F36:F38) -> 71932207 | G39: =SUM(G36:G38) -> 1.2802254e+08 | H39: =SUM(H36:H38) -> 1.9443747e+08
B41: Total Equity & Liability | D41: =D33+D39 -> 3322733.1 | E41: =E33+E39 -> 24539211 | F41: =F33+F39 -> 72051732 | G41: =G33+G39 -> 1.2816606e+08 | H41: =H33+H39 -> 1.9460636e+08
B42: Check | D42: =D41-D24 -> 0 | E42: =E41-E24 -> 0 | F42: =F41-F24 -> 0 | G42: =G41-G24 -> 0 | H42: =H41-H24 -> 0
D48: =YEAR(D49) -> 2026 | E48: =YEAR(E49) -> 2026 | F48: =YEAR(F49) -> 2026 | G48: =YEAR(G49) -> 2026 | H48: =YEAR(H49) -> 2026 | I48: =YEAR(I49) -> 2026 | J48: =YEAR(J49) -> 2026 | K48: =YEAR(K49) -> 2027 | ... BK48: =YEAR(BK49) -> 2031
D49: =PL!D63 -> 46174 | E49: =PL!E63 -> 46234 | F49: =PL!F63 -> 46265 | G49: =PL!G63 -> 46295 | H49: =PL!H63 -> 46326 | I49: =PL!I63 -> 46356 | J49: =PL!J63 -> 46387 | K49: =PL!K63 -> 46418 | ... BK49: =PL!BK63 -> 47999
B50: Assets
B51: Current Assets
B52: Cash/bank | D52: =CF!D54 -> 1088301.4 | E52: =CF!E54 -> 823148.22 | F52: =CF!F54 -> 561588.49 | G52: =CF!G54 -> 645695.94 | H52: =CF!H54 -> 816653.55 | I52: =CF!I54 -> 1004173.5 | J52: =CF!J54 -> 1177533.6 | K52: =CF!K54 -> 1362397.5 | ... BK52: =CF!BK54 -> 1.9092868e+08
B53: Reveivable | D53: =('Assumption Sheet'!$D$12*PL!D66)/365 -> 42739.726 | E53: =('Assumption Sheet'!$D$12*PL!E66)/365 -> 43232.877 | F53: =('Assumption Sheet'!$D$12*PL!F66)/365 -> 43972.603 | G53: =('Assumption Sheet'!$D$12*PL!G66)/365 -> 126910.68 | H53: =('Assumption Sheet'!$D$12*PL!H66)/365 -> 129307.4 | I53: =('Assumption Sheet'!$D$12*PL!I66)/365 -> 131743.69 | J53: =('Assumption Sheet'!$D$12*PL!J66)/365 -> 134220.36 | K53: =('Assumption Sheet'!$D$12*PL!K66)/365 -> 136904.65 | ... BK53: =('Assumption Sheet'!$D$12*PL!BK66)/365 -> 2404385.7
B54: Prepayment | D54: =('Assumption Sheet'!$D$11*PL!D104)/365 -> 65753.425 | E54: =('Assumption Sheet'!$D$11*PL!E104)/365 -> 65753.425 | F54: =('Assumption Sheet'!$D$11*PL!F104)/365 -> 65753.425 | G54: =('Assumption Sheet'!$D$11*PL!G104)/365 -> 65753.425 | H54: =('Assumption Sheet'!$D$11*PL!H104)/365 -> 65753.425 | I54: =('Assumption Sheet'!$D$11*PL!I104)/365 -> 65753.425 | J54: =('Assumption Sheet'!$D$11*PL!J104)/365 -> 65753.425 | K54: =('Assumption Sheet'!$D$11*PL!K104)/365 -> 65753.425 | ... BK54: =('Assumption Sheet'!$D$11*PL!BK104)/365 -> 202671.55
B57: Total Current Assets | D57: =SUM(D52:D56) -> 1196794.5 | E57: =SUM(E52:E56) -> 932134.52 | F57: =SUM(F52:F56) -> 671314.52 | G57: =SUM(G52:G56) -> 838360.05 | H57: =SUM(H52:H56) -> 1011714.4 | I57: =SUM(I52:I56) -> 1201670.6 | J57: =SUM(J52:J56) -> 1377507.4 | K57: =SUM(K52:K56) -> 1565055.6 | ... BK57: =SUM(BK52:BK56) -> 1.9353574e+08
B58: Non-Current Assets
B59: Long Term Asset | D59: =+CAPEX!D40 -> 29000 | E59: =D59+CAPEX!E40 -> 67000 | F59: =E59+CAPEX!F40 -> 105000 | G59: =F59+CAPEX!G40 -> 143000 | H59: =G59+CAPEX!H40 -> 181000 | I59: =H59+CAPEX!I40 -> 210000 | J59: =I59+CAPEX!J40 -> 262000 | K59: =J59+CAPEX!K40 -> 314000 | L59: =K59+CAPEX!L40 -> 366000 | ... BK59: =BJ59+CAPEX!BK40 -> 1582800
B60: Equipment | D60: 0
B61: Intangible Assets | D61: 0
B62: Acc. Depreciation | D62: =+PL!D107 -> 0 | E62: =+D62+PL!E107 -> 290 | F62: =+E62+PL!F107 -> 957.1 | G62: =+F62+PL!G107 -> 1997.529 | H62: =+G62+PL!H107 -> 3407.5537 | I62: =+H62+PL!I107 -> 5183.4782 | J62: =+I62+PL!J107 -> 7231.6434 | K62: =+J62+PL!K107 -> 9779.327 | L62: =+K62+PL!L107 -> 12821.534 | ... BK62: =+BJ62+PL!BK107 -> 512177.13
B64: Total Non-Current Assets | D64: =SUM(D59:D61)-D62 -> 29000 | E64: =SUM(E59:E61)-E62 -> 66710 | F64: =SUM(F59:F61)-F62 -> 104042.9 | G64: =SUM(G59:G61)-G62 -> 141002.47 | H64: =SUM(H59:H61)-H62 -> 177592.45 | I64: =SUM(I59:I61)-I62 -> 204816.52 | J64: =SUM(J59:J61)-J62 -> 254768.36 | K64: =SUM(K59:K61)-K62 -> 304220.67 | ... BK64: =SUM(BK59:BK61)-BK62 -> 1070622.9
B66: Total Assets | D66: =D57+D64 -> 1225794.5 | E66: =E57+E64 -> 998844.52 | F66: =F57+F64 -> 775357.42 | G66: =G57+G64 -> 979362.52 | H66: =H57+H64 -> 1189306.8 | I66: =I57+I64 -> 1406487.1 | J66: =J57+J64 -> 1632275.8 | K66: =K57+K64 -> 1869276.3 | ... BK66: =BK57+BK64 -> 1.9460636e+08
B68: Equity & Liability
B69: Payable | D69: ='Assumption Sheet'!$D$13*PL!D104/365 -> 54794.521 | E69: ='Assumption Sheet'!$D$13*PL!E104/365 -> 54794.521 | F69: ='Assumption Sheet'!$D$13*PL!F104/365 -> 54794.521 | G69: ='Assumption Sheet'!$D$13*PL!G104/365 -> 54794.521 | H69: ='Assumption Sheet'!$D$13*PL!H104/365 -> 54794.521 | I69: ='Assumption Sheet'!$D$13*PL!I104/365 -> 54794.521 | J69: ='Assumption Sheet'!$D$13*PL!J104/365 -> 54794.521 | K69: ='Assumption Sheet'!$D$13*PL!K104/365 -> 54794.521 | ... BK69: ='Assumption Sheet'!$D$13*PL!BK104/365 -> 168892.96
B70: Other Liability | D70: 0 | E70: 0 | F70: 0 | G70: 0 | H70: 0 | I70: 0 | J70: 0 | K70: 0 | L70: 0 | M70: 0 | N70: 0 | O70: 0 | P70: 0 | Q70: 0 | R70: 0 | S70: 0 | T70: 0 | U70: 0 | V70: 0 | W70: 0 | X70: 0 | Y70: 0 | Z70: 0 | AA70: 0 | AB70: 0 | AC70: 0 | AD70: 0 | AE70: 0 | AF70: 0 | AG70: 0 | AH70: 0 | AI70: 0 | AJ70: 0 | AK70: 0 | AL70: 0
B71: Total Current Assets | D71: =SUM(D69:D70) -> 54794.521 | E71: =SUM(E69:E70) -> 54794.521 | F71: =SUM(F69:F70) -> 54794.521 | G71: =SUM(G69:G70) -> 54794.521 | H71: =SUM(H69:H70) -> 54794.521 | I71: =SUM(I69:I70) -> 54794.521 | J71: =SUM(J69:J70) -> 54794.521 | K71: =SUM(K69:K70) -> 54794.521 | ... BK71: =SUM(BK69:BK70) -> 168892.96
B72: Long term Loan
